{
  "titre": "Supprimer les zones à faibles émissions mobilité",
  "sous_titre_1": "Problèmes d'accessibilité aux centres urbains et barrières financières pour les habitants",
  "sous_titre_2": "Remettre un rapport sur des alternatives et réévaluer Crit'Air d'ici six mois",
  "summary_url": "https://www.assemblee-nationale.fr/dyn/16/amendements/0257/AN/25",
  "dossier_url": "",
  "type": "Amendement",
  "date": "2023-01-12",
  "debat_url": "https://theatrebourbon.delemazure.fr/piece?p=97&a=2#r118"
}