{
  "titre": "Exclure les mangas du Pass Culture pour les jeunes",
  "sous_titre_1": "Modifier l'utilisation des crédits du Pass Culture alloués aux jeunes de 15 à 18 ans",
  "sous_titre_2": "Réorienter vers d'autres formes de littérature, le théâtre, les musées ou les concerts de musique classique",
  "summary_url": "https://www.assemblee-nationale.fr/dyn/16/amendements/0273C/AN/1690",
  "dossier_url": "http://www.senat.fr/dossier-legislatif/pjlf2023.html",
  "type": "Amendement",
  "date": "2022-10-28"
}